procin/__init__.py
procin/procin.py
procin-1.1.3.dist-info/AUTHORS.rst
procin-1.1.3.dist-info/LICENSE
procin-1.1.3.dist-info/METADATA
procin-1.1.3.dist-info/WHEEL
procin-1.1.3.dist-info/top_level.txt
procin-1.1.3.dist-info/RECORD
