Metadata-Version: 2.1
Name: procin
Version: 1.1.3
Summary: library to interface to commands that generate output
Home-page: https://github.com/andgrit/procin
Author: Powell Quiring
Author-email: powellquiring@gmail.com
License: MIT license
Keywords: procin
Platform: UNKNOWN
Classifier: Development Status :: 2 - Pre-Alpha
Classifier: Intended Audience :: Developers
Classifier: License :: OSI Approved :: MIT License
Classifier: Natural Language :: English
Classifier: Programming Language :: Python :: 3
Classifier: Programming Language :: Python :: 3.5
Classifier: Programming Language :: Python :: 3.6
Classifier: Programming Language :: Python :: 3.7
Classifier: Programming Language :: Python :: 3.8
Requires-Python: >=3.5
